<?xml version="1.0" encoding="ISO-8859-1"?>
<!--Créé par nmahraz, le 09/03/2022-->
<RetrieveValueSetResponse xmlns:xsi="http://www.w3.org/2001/XMLSchema-instance" xsi:schemaLocation="urn:ihe:iti:svs:2008 SVS.xsd" xmlns="urn:ihe:iti:svs:2008"><ValueSet id="1.2.250.1.213.1.1.5.208" displayName="JDV_ArtereAnt-CISIS" version="test"><ConceptList><Concept code="MED-483" displayName="Perforantes Directes de la Carotide" codeSystem="1.2.250.1.213.1.1.4.322"/><Concept code="MED-459" displayName="Artère cérébrale antérieure territoire superficiel" codeSystem="1.2.250.1.213.1.1.4.322"/><Concept code="MED-460" displayName="Artère cérébrale antérieure territoire profond" codeSystem="1.2.250.1.213.1.1.4.322"/><Concept code="MED-461" displayName="Artère cérébrale antérieure territoires complets" codeSystem="1.2.250.1.213.1.1.4.322"/><Concept code="MED-462" displayName="Artère cérébrale moyenne territoire superficiel" codeSystem="1.2.250.1.213.1.1.4.322"/><Concept code="MED-463" displayName="Artère cérébrale moyenne territoire profond" codeSystem="1.2.250.1.213.1.1.4.322"/><Concept code="MED-464" displayName="Artère cérébrale moyenne territoires complets" codeSystem="1.2.250.1.213.1.1.4.322"/><Concept code="T-45340" displayName="Artère choroïdienne antérieure" codeSystem="1.2.250.1.213.2.12"/></ConceptList></ValueSet></RetrieveValueSetResponse>
